gypsumai_client/__init__.py
gypsumai_client/client.py
gypsumai_client/dataset_manager.py
gypsumai_client/document_manager.py
gypsumai_client/models.py
gypsumai_client/project_manager.py
gypsumai_client-0.1.0.dist-info/LICENSE
gypsumai_client-0.1.0.dist-info/METADATA
gypsumai_client-0.1.0.dist-info/WHEEL
gypsumai_client-0.1.0.dist-info/RECORD
