Metadata-Version: 2.1
Name: gypsumai-client
Version: 0.1.0
Summary: Extract and process unstructured data
Keywords: Gypsum AI,SDK,API,Python
Author: Gypsum AI
Author-email: founders@gypsum.ai
Requires-Python: >=3.9,<3.12
Classifier: Programming Language :: Python :: 3
Classifier: Programming Language :: Python :: 3.9
Classifier: Programming Language :: Python :: 3.10
Classifier: Programming Language :: Python :: 3.11
Requires-Dist: pydantic (>=2.8.2,<3.0.0)
Requires-Dist: pytest (>=8.3.2,<9.0.0)
Requires-Dist: requests (>=2.32.3,<3.0.0)
